django_theme_installer-0.1.6.data/scripts/theme_cli.py
theme_installer/__init__.py
theme_installer/constants.py
theme_installer/core.py
theme_installer/loaders.py
theme_installer/utils.py
theme_installer/management/__init__.py
theme_installer/management/commands/__init__.py
theme_installer/management/commands/theme_install.py
django_theme_installer-0.1.6.dist-info/LICENSE
django_theme_installer-0.1.6.dist-info/METADATA
django_theme_installer-0.1.6.dist-info/WHEEL
django_theme_installer-0.1.6.dist-info/top_level.txt
django_theme_installer-0.1.6.dist-info/RECORD
