Metadata-Version: 2.1
Name: django-theme-installer
Version: 0.1.6
Summary: A Django theme installer
Home-page: https://github.com/jefcolbi/django-theme-installer
Author: jefcolbi
Author-email: jefcolbi@mboatek.com
License: MIT
Platform: UNKNOWN
Classifier: Natural Language :: English
Classifier: Natural Language :: French
Classifier: Development Status :: 5 - Production/Stable
Classifier: Programming Language :: Python
Classifier: Programming Language :: Python :: 3.5
Classifier: Programming Language :: Python :: 3.6
Classifier: Programming Language :: Python :: 3.7
Classifier: License :: OSI Approved :: GNU General Public License v3 or later (GPLv3+)
Requires-Python: >=3.5
Requires-Dist: django
